minipb.py
minipb/__init__.pyi
minipb/py.typed
minipb-2.0.0.dist-info/LICENSE
minipb-2.0.0.dist-info/METADATA
minipb-2.0.0.dist-info/WHEEL
minipb-2.0.0.dist-info/top_level.txt
minipb-2.0.0.dist-info/RECORD
