Metadata-Version: 2.1
Name: minipb
Version: 2.0.0
Summary: Lightweight Protocol Buffer serialize/deserialize library.
Author: dogtopus
License: BSD-3-Clause
Project-URL: repository, https://github.com/dogtopus/minipb
Keywords: protobuf,micropython
Classifier: Development Status :: 4 - Beta
Classifier: License :: OSI Approved :: BSD License
Classifier: Programming Language :: Python :: 3
Classifier: Topic :: Software Development :: Embedded Systems
Classifier: Topic :: Software Development :: Libraries :: Python Modules
Classifier: Typing :: Typed
Requires-Python: >=3.4
License-File: LICENSE
